{"cameraMode":{"drawMode":0,"name":"Shaded","section":"Shading Mode"},"sceneLighting":true,"audioPlay":false,"sceneViewState":{"showFog":true,"showMaterialUpdate":false,"showSkybox":true,"showFlares":true,"showImageEffects":true,"showParticleSystems":true},"in2DMode":false,"pivot":{"x":807.4649658203125,"y":-178.39820861816407,"z":185.9075927734375},"rotation":{"x":0.11979712545871735,"y":0.6285944581031799,"z":-0.09899437427520752,"w":0.7623035907745361},"size":652.9553833007813,"orthographic":false}